dfqueue/__init__.py
dfqueue/__meta__.py
dfqueue/core/__init__.py
dfqueue/core/dfqueue.py
dfqueue/tests/__init__.py
dfqueue/tests/test_assign_dataframe.py
dfqueue/tests/test_list_queue_names.py
dfqueue/tests/test_queue_handler.py
dfqueue/tests/test_queue_info_provider.py
dfqueue/tests/scenarios/__init__.py
dfqueue/tests/scenarios/test_parallel.py
dfqueue/tests/scenarios/test_sequential.py
dfqueue-1.0.dist-info/LICENSE
dfqueue-1.0.dist-info/METADATA
dfqueue-1.0.dist-info/WHEEL
dfqueue-1.0.dist-info/top_level.txt
dfqueue-1.0.dist-info/RECORD
