Metadata-Version: 2.1
Name: dfqueue
Version: 1.0
Summary: Content management decorators for pandas Dataframes
Home-page: https://github.com/JCH222/dfqueue
Author: Jean-Charles Hardy
Author-email: jeancharles.hardy2224@gmail.com
License: MIT
Keywords: queues,pandas-dataframe,decorators
Platform: UNKNOWN
Classifier: Programming Language :: Python :: 3.6
Requires-Dist: pandas (>=0.23.4)
